connectorator/__init__.py
connectorator/complex.py
connectorator/main.py
connectorator-0.1.7.dist-info/METADATA
connectorator-0.1.7.dist-info/WHEEL
connectorator-0.1.7.dist-info/RECORD
